{
  "publicPath": "/_nuxt/",
  "all": [
    "../server/index.spa.html",
    "../server/index.ssr.html",
    "0277bbff0d7489c84f58.js",
    "1961d0006953738782b3.js",
    "2a72f973134701a864fb.js",
    "43ae8b0a53b67c894e2d.js",
    "465521dde8387b948a2b.js",
    "93020afb500b1658d99f.js",
    "LICENSES",
    "aab9a485258ca7e3894d.js",
    "b5899cf1c5c1b6e5d5f2.js",
    "c2387db00ffe7e96a1e0.js",
    "img/42a44be.jpeg",
    "img/6cbc81b.jpg",
    "img/a1ec89f.svg",
    "img/ca1ef68.png",
    "img/ee5895c.png"
  ],
  "initial": [
    "465521dde8387b948a2b.js",
    "2a72f973134701a864fb.js",
    "0277bbff0d7489c84f58.js"
  ],
  "async": [
    "1961d0006953738782b3.js",
    "43ae8b0a53b67c894e2d.js",
    "93020afb500b1658d99f.js",
    "aab9a485258ca7e3894d.js",
    "b5899cf1c5c1b6e5d5f2.js",
    "c2387db00ffe7e96a1e0.js"
  ],
  "modules": {
    "14471994": [
      9
    ],
    "22211060": [
      4
    ],
    "22860004": [
      4
    ],
    "30505785": [
      9
    ],
    "30998744": [
      9
    ],
    "31751681": [
      9
    ],
    "31959026": [
      4
    ],
    "40228550": [
      9
    ],
    "48904498": [
      9
    ],
    "49504086": [
      4
    ],
    "49711020": [
      9
    ],
    "50504442": [
      9
    ],
    "53517106": [
      9
    ],
    "68598968": [
      9
    ],
    "69050479": [
      5,
      13
    ],
    "70078062": [
      4
    ],
    "82214304": [
      2,
      14,
      16,
      15
    ],
    "82978014": [
      9
    ],
    "8c2889e4": [
      4
    ],
    "e0a54d22": [
      4
    ],
    "0cfa3a3a": [
      4
    ],
    "f3d2f7c6": [
      4
    ],
    "7244959d": [
      4
    ],
    "c5b8ee9e": [
      4
    ],
    "261c718a": [
      4
    ],
    "4c201922": [
      4
    ],
    "efb7a328": [
      4
    ],
    "61c2c6d8": [
      4
    ],
    "0016c7a8": [
      4
    ],
    "788e1008": [
      2,
      14,
      16,
      15
    ],
    "71b95b44": [
      2,
      14,
      16,
      15
    ],
    "5526caf9": [
      4
    ],
    "1c24e81c": [
      4
    ],
    "4ade9ce1": [
      4
    ],
    "485b685e": [
      4
    ],
    "7587bd14": [
      4
    ],
    "3343b3c5": [
      4
    ],
    "6dbee234": [
      4
    ],
    "34d7c828": [
      4
    ],
    "8d6d2a6c": [
      4
    ],
    "cdfd1830": [
      4
    ],
    "eca87072": [
      4
    ],
    "b5d2f452": [
      4
    ],
    "4dc617d3": [
      4
    ],
    "e7beb0c4": [
      4
    ],
    "6e0d8667": [
      4
    ],
    "7cb7e0c9": [
      4
    ],
    "5a25226b": [
      4
    ],
    "6ddff2b4": [
      4
    ],
    "d29ce5f6": [
      4
    ],
    "df959048": [
      4
    ],
    "34e81f49": [
      4
    ],
    "28e49762": [
      4
    ],
    "567b42c3": [
      4
    ],
    "12d1c6d1": [
      2,
      14,
      16,
      15
    ],
    "5b6599a9": [
      2,
      14,
      16,
      15
    ],
    "7deb243c": [
      2,
      14,
      16,
      15
    ],
    "b76f2276": [
      2,
      14,
      16,
      15
    ],
    "2aafad1d": [
      2,
      14,
      16,
      15
    ],
    "1b978808": [
      2,
      14,
      16,
      15
    ],
    "1a7fbeda": [
      2,
      14,
      16,
      15
    ],
    "3716f8b1": [
      2,
      14,
      16,
      15
    ],
    "0020d0aa": [
      4
    ],
    "228a8bba": [
      4
    ],
    "1018cd8e": [
      4
    ],
    "4582fcd9": [
      4
    ],
    "53c6df36": [
      4
    ],
    "42ecd46e": [
      4
    ],
    "10b20c1b": [
      4
    ],
    "0aba84d6": [
      4
    ],
    "0103ec3d": [
      4
    ],
    "228cd195": [
      4
    ],
    "2b2b7784": [
      4
    ],
    "56d8da22": [
      4
    ],
    "50abb93c": [
      4
    ],
    "4cded592": [
      4
    ],
    "e5c3c772": [
      4
    ],
    "5162750c": [
      4
    ],
    "db3c2e38": [
      4
    ],
    "50651d38": [
      2,
      14,
      16,
      15
    ],
    "386bf5a4": [
      4
    ],
    "739088fa": [
      4
    ],
    "9826e244": [
      4
    ],
    "168abc6e": [
      4
    ],
    "2c263178": [
      4
    ],
    "880538fe": [
      4
    ],
    "5ba2b955": [
      4
    ],
    "52704f4f": [
      4
    ],
    "3040a352": [
      4
    ],
    "befb03ca": [
      4
    ],
    "c36f15de": [
      4
    ],
    "19175bd7": [
      4
    ],
    "36a05666": [
      4
    ],
    "441b12cc": [
      4
    ],
    "4bbe8466": [
      4
    ],
    "2e012ec7": [
      4
    ],
    "5f87cabf": [
      4
    ],
    "05ad7a65": [
      4
    ],
    "9354f58a": [
      4
    ],
    "6320c22e": [
      4
    ],
    "689a0418": [
      4
    ],
    "0266eb06": [
      4
    ],
    "06b0367a": [
      4
    ],
    "476e8624": [
      4
    ],
    "c3c1b690": [
      4
    ],
    "6557f8b6": [
      4
    ],
    "1b78f535": [
      4
    ],
    "645532e0": [
      4
    ],
    "5b60032e": [
      4
    ],
    "777631d3": [
      4
    ],
    "ed3180b4": [
      4
    ],
    "74ee7ada": [
      2,
      14,
      16,
      15
    ],
    "64b595b4": [
      4
    ],
    "0a18f3b2": [
      4
    ],
    "f8def48e": [
      4
    ],
    "63fa16ac": [
      4
    ],
    "282a977d": [
      4
    ],
    "8176035e": [
      4
    ],
    "3fadabd8": [
      2,
      14,
      16,
      15
    ],
    "202a7edf": [
      4
    ],
    "23def3fd": [
      4
    ],
    "14d371a7": [
      4
    ],
    "19f02a08": [
      4
    ],
    "4ae6d4bb": [
      4
    ],
    "3952fd6e": [
      4
    ],
    "212730aa": [
      4
    ],
    "419792e6": [
      4
    ],
    "5db2eb89": [
      4
    ],
    "2d97654c": [
      4
    ],
    "35e434ad": [
      4
    ],
    "694f2cd1": [
      4
    ],
    "4bef658a": [
      4
    ],
    "2164dece": [
      4
    ],
    "6e7a0365": [
      4
    ],
    "7115804a": [
      4
    ],
    "16c02782": [
      4
    ],
    "5837e0b5": [
      4
    ],
    "07661728": [
      4
    ],
    "38e21476": [
      4
    ],
    "2dfee926": [
      4
    ],
    "a0dcbe86": [
      4
    ],
    "b9e0d0c4": [
      4
    ],
    "ddc78e14": [
      4
    ],
    "dc3e8998": [
      4
    ],
    "666fdefa": [
      4
    ],
    "3e032370": [
      4
    ],
    "503231ae": [
      2,
      14,
      16,
      15
    ],
    "4daaa3d8": [
      4
    ],
    "181890ed": [
      4
    ],
    "53668ef7": [
      4
    ],
    "18001d2a": [
      4
    ],
    "a77ef0f2": [
      4
    ],
    "5d4b1934": [
      4
    ],
    "cacde018": [
      4
    ],
    "169d1ad1": [
      4
    ],
    "8ab4e12e": [
      4
    ],
    "235d2524": [
      2,
      14,
      16,
      15
    ],
    "8e25a3ae": [
      2,
      14,
      16,
      15
    ],
    "c17032b4": [
      2,
      14,
      16,
      15
    ],
    "92ac4dfe": [
      2,
      14,
      16,
      15
    ],
    "190d3d86": [
      2,
      14,
      16,
      15
    ],
    "1a1f2eca": [
      2,
      14,
      16,
      15
    ],
    "33c5338a": [
      2,
      14,
      16,
      15
    ],
    "0402b06d": [
      2,
      14,
      16,
      15
    ],
    "177b5ab4": [
      2,
      14,
      16,
      15
    ],
    "13c7e2c6": [
      2,
      14,
      16,
      15
    ],
    "75b6a8da": [
      2,
      14,
      16,
      15
    ],
    "534f3acc": [
      4
    ],
    "5fed25f9": [
      4
    ],
    "5653bfc7": [
      4
    ],
    "e233e1b2": [
      4
    ],
    "6c873c50": [
      4
    ],
    "06e12bc1": [
      4
    ],
    "4033a37b": [
      4
    ],
    "3fb3e644": [
      4
    ],
    "1f65b3c6": [
      4
    ],
    "5062b4ea": [
      4
    ],
    "3cf3e127": [
      4
    ],
    "48129b74": [
      4
    ],
    "16dfb8c4": [
      4
    ],
    "3bbad2e9": [
      4
    ],
    "33d60722": [
      4
    ],
    "502e0bef": [
      4
    ],
    "12e61e16": [
      2,
      14,
      16,
      15
    ],
    "ad6dea9c": [
      2,
      14,
      16,
      15
    ],
    "4ba9a2fc": [
      2,
      14,
      16,
      15
    ],
    "599ce85e": [
      2,
      14,
      16,
      15
    ],
    "d16d71b8": [
      2,
      14,
      16,
      15
    ],
    "d08e62f2": [
      2,
      14,
      16,
      15
    ],
    "641b6cb2": [
      2,
      14,
      16,
      15
    ],
    "58380b2f": [
      2,
      14,
      16,
      15
    ],
    "0b500644": [
      2,
      14,
      16,
      15
    ],
    "07fef409": [
      2,
      14,
      16,
      15
    ],
    "591f2606": [
      2,
      14,
      16,
      15
    ],
    "765d755a": [
      2,
      14,
      16,
      15
    ],
    "6904d4b2": [
      9
    ],
    "8df0b1be": [
      5,
      13
    ],
    "5104d197": [
      10,
      13
    ],
    "f8a10fba": [
      10,
      13
    ],
    "60d99bc2": [
      3,
      13
    ],
    "4870c85f": [
      9
    ],
    "059cf64e": [
      9
    ],
    "e4505e14": [
      9
    ],
    "af0b4076": [
      11,
      13
    ],
    "11ccb0c0": [
      7,
      12
    ],
    "3c7923ec": [
      9
    ],
    "2ecde764": [
      9
    ],
    "bec946a8": [
      9
    ],
    "33a2bc62": [
      9
    ],
    "596198d6": [
      9
    ],
    "54867b5c": [
      9
    ],
    "112e731a": [
      9
    ],
    "c6f2af36": [
      9
    ],
    "4a848f94": [
      5,
      13
    ],
    "2d2385b4": [
      10,
      13
    ],
    "a71a6c60": [
      10,
      13
    ],
    "21600f96": [
      10,
      13
    ],
    "13cc4682": [
      10,
      13
    ],
    "12ed37bc": [
      10,
      13
    ],
    "509a13fb": [
      10,
      13
    ],
    "3f538a90": [
      10,
      13
    ],
    "3ce28b9a": [
      3,
      13
    ],
    "9ef9e852": [
      3,
      13
    ],
    "2f7e3324": [
      9
    ],
    "35499da7": [
      9
    ],
    "49f13133": [
      9
    ],
    "d58559de": [
      9
    ],
    "2d887a63": [
      9
    ],
    "4b666b88": [
      9
    ],
    "261fa0d9": [
      9
    ],
    "31502a54": [
      9
    ],
    "54d8574a": [
      9
    ],
    "76f22ae7": [
      9
    ],
    "527bb0f4": [
      9
    ],
    "4ca51d94": [
      9
    ],
    "fbffd0de": [
      9
    ],
    "0551c37c": [
      9
    ],
    "2e8081ce": [
      9
    ],
    "c6f7bf32": [
      9
    ],
    "384e6af4": [
      9
    ],
    "7ffd819b": [
      9
    ],
    "66b81bb7": [
      9
    ],
    "52b7c2b8": [
      9
    ],
    "665c4afc": [
      9
    ],
    "0dc58b21": [
      9
    ],
    "a9ddb36a": [
      9
    ],
    "b157e8a8": [
      9
    ],
    "4e4f81aa": [
      9
    ],
    "42bb0c2d": [
      9
    ],
    "2e2602e1": [
      9
    ],
    "40874a50": [
      9
    ],
    "366ebb55": [
      9
    ],
    "776300bd": [
      9
    ],
    "6f22f6c8": [
      9
    ],
    "1cad9d04": [
      9
    ],
    "4cc063d8": [
      9
    ],
    "4cbe925c": [
      9
    ],
    "e6e340b4": [
      9
    ],
    "cf681c7a": [
      9
    ],
    "4c50908e": [
      9
    ],
    "4c4dd654": [
      9
    ],
    "439ef755": [
      9
    ],
    "f2e0a7b4": [
      9
    ],
    "77895e96": [
      9
    ],
    "1927e7af": [
      9
    ],
    "f6fea760": [
      9
    ],
    "5197a48c": [
      9
    ],
    "96f25a4e": [
      9
    ],
    "4954e11e": [
      9
    ],
    "680bc544": [
      9
    ],
    "48c7f614": [
      9
    ],
    "cc8f3afa": [
      9
    ],
    "a4349180": [
      9
    ],
    "18ca5a54": [
      9
    ],
    "4645315a": [
      9
    ],
    "7d62565b": [
      9
    ],
    "45a61778": [
      9
    ],
    "35302b90": [
      9
    ],
    "4ad2de0c": [
      9
    ],
    "f03ba1bc": [
      9
    ],
    "43260cf8": [
      9
    ],
    "18c3bc40": [
      9
    ],
    "12b030c5": [
      9
    ],
    "035fb531": [
      9
    ],
    "15f52675": [
      9
    ],
    "93162e44": [
      9
    ],
    "152a8de5": [
      9
    ],
    "3d5daab7": [
      9
    ],
    "290bd3b7": [
      9
    ],
    "3086e40d": [
      9
    ],
    "2dc9162a": [
      9
    ],
    "7b875564": [
      9
    ],
    "8ba237b2": [
      9
    ],
    "4ad8331d": [
      9
    ],
    "bd8f1be6": [
      9
    ],
    "55b93245": [
      9
    ],
    "4b70070f": [
      9
    ],
    "3b401a58": [
      9
    ],
    "7fbbd2ac": [
      9
    ],
    "6ba8bced": [
      9
    ],
    "74caec0b": [
      9
    ],
    "3869b156": [
      9
    ],
    "04c596ff": [
      9
    ],
    "95c305da": [
      9
    ],
    "3ad9a130": [
      9
    ],
    "41a02262": [
      9
    ],
    "590e06e6": [
      9
    ],
    "00245940": [
      9
    ],
    "1eab449c": [
      9
    ],
    "537cf358": [
      9
    ],
    "8b217302": [
      9
    ],
    "235491c0": [
      9
    ],
    "2498ae57": [
      9
    ],
    "259c3e3c": [
      9
    ],
    "2c6e439b": [
      9
    ],
    "789fae19": [
      9
    ],
    "6367a844": [
      9
    ],
    "31b5b6de": [
      9
    ],
    "2d9cf858": [
      9
    ],
    "2d6e9a7e": [
      9
    ],
    "6859decb": [
      9
    ],
    "4bd18916": [
      9
    ],
    "5003bfa8": [
      9
    ],
    "1f26c87c": [
      9
    ],
    "2bbdd936": [
      9
    ],
    "78cf1cc6": [
      9
    ],
    "2669e9bd": [
      9
    ],
    "5710206c": [
      9
    ],
    "0db835b4": [
      9
    ],
    "c6b9d154": [
      9
    ],
    "81066b7c": [
      9
    ],
    "6f4d2969": [
      9
    ],
    "368d56d7": [
      9
    ],
    "9377a142": [
      9
    ],
    "87ed8740": [
      9
    ],
    "27d88308": [
      9
    ],
    "b280bb34": [
      9
    ],
    "4462916b": [
      9
    ],
    "3cd21e4d": [
      9
    ],
    "96cd52d0": [
      9
    ],
    "1caf3858": [
      9
    ],
    "37900c45": [
      9
    ],
    "3101a03f": [
      9
    ],
    "2128957e": [
      9
    ],
    "0a01e62b": [
      9
    ],
    "1d2783ca": [
      9
    ],
    "69dc3002": [
      9
    ],
    "2f5c7270": [
      9
    ],
    "29e523c4": [
      9
    ],
    "d05d6fec": [
      9
    ],
    "5de39041": [
      9
    ],
    "613c277a": [
      9
    ],
    "7836c6ce": [
      9
    ],
    "43a4e028": [
      9
    ],
    "1d359c2e": [
      9
    ],
    "43a55487": [
      9
    ],
    "1a45be64": [
      9
    ],
    "1e3f2972": [
      9
    ],
    "1922d0e4": [
      9
    ],
    "e6fbf8ec": [
      9
    ],
    "7e4fa011": [
      9
    ],
    "47788b9a": [
      9
    ],
    "134e7730": [
      9
    ],
    "537c27a1": [
      9
    ],
    "d703a876": [
      9
    ],
    "28c975ee": [
      9
    ],
    "2574a496": [
      9
    ],
    "1caebdb4": [
      9
    ],
    "166239b2": [
      9
    ],
    "15f6f21e": [
      9
    ],
    "15f17daa": [
      9
    ],
    "9efebd32": [
      9
    ],
    "5ffe658c": [
      9
    ],
    "69fe010a": [
      9
    ],
    "ee15323a": [
      9
    ],
    "b70deb16": [
      9
    ],
    "0b9b3646": [
      9
    ],
    "25ecb8e0": [
      9
    ],
    "63bbbb24": [
      9
    ],
    "14125e88": [
      9
    ],
    "13cf179c": [
      9
    ],
    "7322b2c8": [
      9
    ],
    "313e89f9": [
      9
    ],
    "2a1a1818": [
      9
    ],
    "2f5c5915": [
      9
    ],
    "1653f7b0": [
      9
    ],
    "33cea4c4": [
      9
    ],
    "b9bba350": [
      9
    ],
    "3d3b679b": [
      9
    ],
    "3ae2897b": [
      9
    ],
    "0c94f942": [
      9
    ],
    "2a5f5390": [
      9
    ],
    "56f5a5a5": [
      9
    ],
    "c5e46eae": [
      9
    ],
    "13185a33": [
      9
    ],
    "e4ce407a": [
      9
    ],
    "3505cc82": [
      9
    ],
    "0c526cac": [
      9
    ],
    "471bbb01": [
      9
    ],
    "6ee59de3": [
      9
    ],
    "26edb968": [
      9
    ],
    "79ea15a8": [
      9
    ],
    "697d2fc7": [
      9
    ],
    "782f6f7a": [
      9
    ],
    "7540f240": [
      9
    ],
    "7d816196": [
      9
    ],
    "b494d088": [
      9
    ],
    "081b7370": [
      9
    ],
    "1185205a": [
      9
    ],
    "59c092da": [
      9
    ],
    "27bff22e": [
      9
    ],
    "0e0b42f6": [
      9
    ],
    "7a6ca1b4": [
      9
    ],
    "72ced607": [
      9
    ],
    "743f91ba": [
      9
    ],
    "20c1885c": [
      9
    ],
    "0084828b": [
      9
    ],
    "41ee04f0": [
      9
    ],
    "39c84f48": [
      9
    ],
    "266430b4": [
      9
    ],
    "34fcfccb": [
      9
    ],
    "9c839d92": [
      9
    ],
    "00d1de24": [
      9
    ],
    "6b5b3952": [
      9
    ],
    "8d68b882": [
      9
    ],
    "47cd0e7c": [
      9
    ],
    "610a1b29": [
      9
    ],
    "3ae3a02a": [
      9
    ],
    "14bf6bda": [
      9
    ],
    "4db66836": [
      9
    ],
    "f13c57d8": [
      9
    ],
    "2d7bbd39": [
      9
    ],
    "7e4a1480": [
      9
    ],
    "5c875d04": [
      9
    ],
    "331b4bb2": [
      9
    ],
    "6d7f1192": [
      9
    ],
    "6ea35100": [
      9
    ],
    "4aa73f1e": [
      9
    ],
    "4a4d2d57": [
      9
    ],
    "3900a024": [
      9
    ],
    "a6c33a0c": [
      9
    ],
    "c7d9de14": [
      9
    ],
    "54f0382e": [
      9
    ],
    "084ed390": [
      9
    ],
    "c7136bb6": [
      9
    ],
    "0b480dae": [
      9
    ],
    "731de21c": [
      9
    ],
    "970e7468": [
      9
    ],
    "7334e2da": [
      9
    ],
    "47a5837e": [
      9
    ],
    "58d89a50": [
      9
    ],
    "13dc83c2": [
      9
    ],
    "51ccf87c": [
      9
    ],
    "dd86de74": [
      9
    ],
    "29e52120": [
      9
    ],
    "f42d5e5c": [
      9
    ],
    "08cdde9d": [
      9
    ],
    "1a095737": [
      9
    ],
    "3a5740e8": [
      9
    ],
    "03944b32": [
      9
    ],
    "3e75d7ca": [
      9
    ],
    "7f437e9b": [
      9
    ],
    "027a22ff": [
      9
    ],
    "aef7f1d0": [
      9
    ],
    "8aebdcc6": [
      11,
      13
    ],
    "0faac39a": [
      11,
      13
    ],
    "3805bf14": [
      7,
      12
    ],
    "1d760de8": [
      7,
      12
    ],
    "1b7c35ea": [
      7,
      12
    ],
    "4583d061": [
      10,
      13
    ],
    "5adc7709": [
      11,
      13
    ],
    "01ea35fe": [
      5,
      13
    ],
    "b05ff04a": [
      3,
      13
    ],
    "1ec2bfc6": [
      7,
      12
    ]
  },
  "assetsMapping": {
    "0277bbff0d7489c84f58.js": "1a3ae26b",
    "1961d0006953738782b3.js": "2098cd80",
    "2a72f973134701a864fb.js": "0859c165",
    "43ae8b0a53b67c894e2d.js": "2aff1868",
    "465521dde8387b948a2b.js": "6fca0322",
    "93020afb500b1658d99f.js": "2a130dde",
    "aab9a485258ca7e3894d.js": "6364b351",
    "b5899cf1c5c1b6e5d5f2.js": "acf14974",
    "c2387db00ffe7e96a1e0.js": "9bc09da4"
  }
}